{
  "poolRules": {
    "500": {
      "minSwapUsd": 70000,
      "minNetProfitUsd": 25,
      "enabled": true,
      "priority": 2
    },
    "3000": {
      "minSwapUsd": 15000,
      "minNetProfitUsd": 25,
      "enabled": true,
      "priority": 1
    }
  },
  "simulation": {
    "captureFraction": 0.9,
    "inclusionProbability": 0.4,
    "minScore": 0.0,
    "maxPositions": 10
  },
  "gas": {
    "gasPerPosition": 210000,
    "gasPriceWei": "15000000000",
    "maxGasCostUsd": 100
  },
  "risk": {
    "maxInventoryUsd": 500000,
    "maxLossPercentage": 2.0,
    "positionTimeoutMs": 300000
  },
  "ranges": {
    "narrowWidth": 10,
    "wideWidth": 30,
    "defaultWidth": 20,
    "volatilityThreshold": 0.05
  }
}